koreatrain/__init__.py
koreatrain/constants.py
koreatrain/dataclass.py
koreatrain/errors.py
koreatrain/koreatrain.py
koreatrain/tools.py
KoreaTrain-0.0.1.dist-info/LICENSE
KoreaTrain-0.0.1.dist-info/METADATA
KoreaTrain-0.0.1.dist-info/WHEEL
KoreaTrain-0.0.1.dist-info/top_level.txt
KoreaTrain-0.0.1.dist-info/RECORD
